libaarhusxyz/__init__.py
libaarhusxyz/alc.py
libaarhusxyz/gex.py
libaarhusxyz/normalizer.csv
libaarhusxyz/normalizer.py
libaarhusxyz/normalizer_pattern.csv
libaarhusxyz/sr2.py
libaarhusxyz/survey.py
libaarhusxyz/transforms.py
libaarhusxyz/xyz.py
libaarhusxyz/xyzparser.py
libaarhusxyz/export/__init__.py
libaarhusxyz/export/geojson.py
libaarhusxyz/export/msgpack.py
libaarhusxyz/export/vtk.py
libaarhusxyz-0.0.33.dist-info/licenses/LICENSE
tests/__init__.py
tests/test_export.py
tests/test_parsing.py
tests/utils.py
libaarhusxyz-0.0.33.dist-info/METADATA
libaarhusxyz-0.0.33.dist-info/WHEEL
libaarhusxyz-0.0.33.dist-info/top_level.txt
libaarhusxyz-0.0.33.dist-info/RECORD
