Metadata-Version: 2.4
Name: libaarhusxyz
Version: 0.0.33
Summary: Parser for the Aarhus Workbench XYZ format for geophysical data
Home-page: https://github.com/emerald-geomodelling/libaarhusxyz
Author: Egil Moeller, Craig William Christensen and others 
Author-email: em@emeraldgeo.no, cch@emeraldgeo.no
License-File: LICENSE
Requires-Dist: numpy
Requires-Dist: pandas
Requires-Dist: pyproj
Requires-Dist: matplotlib
Provides-Extra: normalisation
Requires-Dist: pryproj; extra == "normalisation"
Requires-Dist: projnames; extra == "normalisation"
Provides-Extra: tests
Requires-Dist: nose2; extra == "tests"
Requires-Dist: downfile; extra == "tests"
Dynamic: author
Dynamic: author-email
Dynamic: description
Dynamic: description-content-type
Dynamic: home-page
Dynamic: license-file
Dynamic: provides-extra
Dynamic: requires-dist
Dynamic: summary
